README.md
setup.cfg
setup.py
twittertail/__init__.py
twittertail/__main__.py
twittertail/exceptions.py
twittertail/get_tweets_api.py
twittertail/get_twitter_values.py
twittertail/http_server.py
twittertail/render_tweets.py
twittertail/twittertail.py
twittertail.egg-info/PKG-INFO
twittertail.egg-info/SOURCES.txt
twittertail.egg-info/dependency_links.txt
twittertail.egg-info/entry_points.txt
twittertail.egg-info/requires.txt
twittertail.egg-info/top_level.txt