Metadata-Version: 1.1
Name: twittertail
Version: 0.3
Summary: Tail a twitter account from the command line.
Home-page: https://github.com/ndavison/twittertail
Author: Nathan Davison
Author-email: ndavison85@gmail.com
License: MIT
Download-URL: https://github.com/ndavison/twittertail/archive/v03.tar.gz
Keywords: twitter,tweets,cli
Platform: UNKNOWN
Classifier: License :: OSI Approved :: MIT License
Classifier: Programming Language :: Python
Classifier: Programming Language :: Python :: 3
Classifier: Programming Language :: Python :: 3.7
Classifier: Programming Language :: Python :: 3.8
